datahub_custom_transformers/__init__.py
datahub_custom_transformers/domain_structured_properties/__init__.py
datahub_custom_transformers/domain_structured_properties/transformer.py
datahub_custom_transformers-0.2.1.dist-info/METADATA
datahub_custom_transformers-0.2.1.dist-info/WHEEL
datahub_custom_transformers-0.2.1.dist-info/entry_points.txt
datahub_custom_transformers-0.2.1.dist-info/licenses/LICENSE
datahub_custom_transformers-0.2.1.dist-info/RECORD
