Metadata-Version: 2.4
Name: datahub-custom-transformers
Version: 0.2.1
Summary: Collection of custom DataHub transformers for metadata enhancement
Project-URL: Homepage, https://github.com/your-org/datahub-custom-transformers
Project-URL: Documentation, https://github.com/your-org/datahub-custom-transformers#readme
Project-URL: Repository, https://github.com/your-org/datahub-custom-transformers.git
Project-URL: Issues, https://github.com/your-org/datahub-custom-transformers/issues
Author: Abdullah Tariq
License-Expression: MIT
License-File: LICENSE
Keywords: custom-transformers,data-catalog,data-governance,datahub,metadata,transformers
Classifier: Development Status :: 4 - Beta
Classifier: Intended Audience :: Developers
Classifier: License :: OSI Approved :: MIT License
Classifier: Operating System :: OS Independent
Classifier: Programming Language :: Python :: 3
Classifier: Programming Language :: Python :: 3.10
Classifier: Programming Language :: Python :: 3.11
Classifier: Programming Language :: Python :: 3.12
Classifier: Programming Language :: Python :: 3.13
Classifier: Topic :: Database
Classifier: Topic :: Software Development :: Libraries :: Python Modules
Requires-Python: >=3.10
Requires-Dist: acryl-datahub>=0.12.0
Requires-Dist: pydantic>=1.8.0
